aiobale/__init__.py
aiobale/exceptions.py
aiobale/logger.py
aiobale/client/auth_cli.py
aiobale/client/client.py
aiobale/client/context_controller.py
aiobale/client/session/__init__.py
aiobale/client/session/aiohttp.py
aiobale/client/session/base.py
aiobale/dispatcher/__init__.py
aiobale/dispatcher/dispatcher.py
aiobale/dispatcher/router.py
aiobale/dispatcher/event/__init__.py
aiobale/dispatcher/event/handler.py
aiobale/dispatcher/event/observer.py
aiobale/enums/__init__.py
aiobale/enums/auth_errors.py
aiobale/enums/chat_type.py
aiobale/enums/gift_openning.py
aiobale/enums/giving_type.py
aiobale/enums/group_type.py
aiobale/enums/list_load_mode.py
aiobale/enums/peer_source.py
aiobale/enums/peer_type.py
aiobale/enums/privacy_mode.py
aiobale/enums/report_kind.py
aiobale/enums/restriction.py
aiobale/enums/send_code.py
aiobale/enums/send_type.py
aiobale/enums/services.py
aiobale/enums/typing_type.py
aiobale/filters/__init__.py
aiobale/filters/base.py
aiobale/filters/chat.py
aiobale/filters/content.py
aiobale/filters/logic.py
aiobale/filters/regex.py
aiobale/methods/__init__.py
aiobale/methods/base.py
aiobale/methods/abacus/__init__.py
aiobale/methods/abacus/get_message_reactions_list.py
aiobale/methods/abacus/get_messages_reaction.py
aiobale/methods/abacus/get_messages_views.py
aiobale/methods/abacus/message_remove_reaction.py
aiobale/methods/abacus/message_set_reaction.py
aiobale/methods/auth/__init__.py
aiobale/methods/auth/sign_out.py
aiobale/methods/auth/sign_up.py
aiobale/methods/auth/start_phone_auth.py
aiobale/methods/auth/validate_code.py
aiobale/methods/auth/validate_password.py
aiobale/methods/configs/__init__.py
aiobale/methods/configs/edit_parameter.py
aiobale/methods/configs/get_parameters.py
aiobale/methods/files/__init__.py
aiobale/methods/files/get_file_upload_url.py
aiobale/methods/files/get_file_url.py
aiobale/methods/giftpacket/__init__.py
aiobale/methods/giftpacket/open_packet.py
aiobale/methods/giftpacket/send_gift_packet_with_wallet.py
aiobale-0.1.5.dist-info/licenses/LICENSE
aiobale-0.1.5.dist-info/METADATA
aiobale-0.1.5.dist-info/WHEEL
aiobale-0.1.5.dist-info/top_level.txt
aiobale-0.1.5.dist-info/RECORD
