Metadata-Version: 2.4
Name: aiobale
Version: 0.1.5
Summary: Modern async client for Bale.
Author-email: Alireza Jahani <mrbansti@gmail.com>
License: MIT License
Project-URL: Homepage, https://docs.aiobale.ir
Project-URL: Repository, https://github.com/Enalite/aiobale
Requires-Python: >=3.8
License-File: LICENSE
Requires-Dist: aiohttp<4.0,>=3.9
Requires-Dist: aiofiles<24.0,>=23.1
Requires-Dist: colorama<1.0,>=0.4.6
Requires-Dist: pydantic<3.0,>=2.0
Requires-Dist: typing_extensions<5.0,>=4.0
Requires-Dist: blackboxprotobuf<2.0,>=1.0.1
Requires-Dist: magic-filter<2.0,>=1.0
Dynamic: license-file
